vidaug/__init__.py
vidaug/augmentors/__init__.py
vidaug/augmentors/affine.py
vidaug/augmentors/crop.py
vidaug/augmentors/flip.py
vidaug/augmentors/geometric.py
vidaug/augmentors/group.py
vidaug/augmentors/intensity.py
vidaug/augmentors/temporal.py
vidaug-1.5.dist-info/LICENSE
vidaug-1.5.dist-info/METADATA
vidaug-1.5.dist-info/WHEEL
vidaug-1.5.dist-info/top_level.txt
vidaug-1.5.dist-info/RECORD
