Metadata-Version: 2.1
Name: vidaug
Version: 1.5
Summary: Video Augmentation Library
Home-page: https://github.com/okankop/vidaug
Author: Okan Kopuklu
Author-email: okankopuklu@gmail.com
License: MIT
Platform: UNKNOWN
